game_vision/__init__.py
game_vision/detector.py
game_vision/exceptions.py
game_vision/trainer.py
game_vision/utils.py
game_vision_yolo-0.1.1.dist-info/METADATA
game_vision_yolo-0.1.1.dist-info/WHEEL
game_vision_yolo-0.1.1.dist-info/top_level.txt
game_vision_yolo-0.1.1.dist-info/RECORD
